NeuroGraph/__init__.py
NeuroGraph/datasets.py
NeuroGraph/preprocess.py
NeuroGraph/test.py
NeuroGraph/utils.py
NeuroGraph-3.0.0.dist-info/LICENSE.txt
NeuroGraph-3.0.0.dist-info/METADATA
NeuroGraph-3.0.0.dist-info/WHEEL
NeuroGraph-3.0.0.dist-info/top_level.txt
NeuroGraph-3.0.0.dist-info/RECORD
